color_extractor/__init__.py
color_extractor/color_extractor.py
test/__init__.py
test/test.py
color_extractor-1.0.0.dist-info/LICENSE
color_extractor-1.0.0.dist-info/METADATA
color_extractor-1.0.0.dist-info/WHEEL
color_extractor-1.0.0.dist-info/top_level.txt
color_extractor-1.0.0.dist-info/RECORD
