Metadata-Version: 2.1
Name: color-extractor
Version: 1.0.0
Summary: A Python package to extract main colors from images.
Home-page: https://github.com/Mizu0927/extract_main_color
Author: Mizuha Kojima
Author-email: s2222076@stu.musashino-u.ac.jp
License: MIT
Classifier: Development Status :: 5 - Production/Stable
Classifier: Intended Audience :: Developers
Classifier: Topic :: Software Development :: Libraries
Classifier: License :: OSI Approved :: MIT License
Classifier: Programming Language :: Python :: 3
Classifier: Programming Language :: Python :: 3.6
Classifier: Programming Language :: Python :: 3.7
Classifier: Programming Language :: Python :: 3.8
Classifier: Programming Language :: Python :: 3.9
License-File: LICENSE
Requires-Dist: opencv-python
Requires-Dist: numpy
Requires-Dist: matplotlib
Requires-Dist: scikit-learn
